LICENSE
MANIFEST.in
README.md
pyproject.toml
requirements.txt
setup.cfg
setup.py
diffusion_webui/__init__.py
diffusion_webui.egg-info/PKG-INFO
diffusion_webui.egg-info/SOURCES.txt
diffusion_webui.egg-info/dependency_links.txt
diffusion_webui.egg-info/requires.txt
diffusion_webui.egg-info/top_level.txt
diffusion_webui/diffusion_models/__init__.py
diffusion_webui/diffusion_models/base_controlnet_pipeline.py
diffusion_webui/diffusion_models/controlnet_inpaint_pipeline.py
diffusion_webui/diffusion_models/controlnet_pipeline.py
diffusion_webui/diffusion_models/img2img_app.py
diffusion_webui/diffusion_models/inpaint_app.py
diffusion_webui/diffusion_models/text2img_app.py
diffusion_webui/utils/__init__.py
diffusion_webui/utils/data_utils.py
diffusion_webui/utils/model_list.py
diffusion_webui/utils/preprocces_utils.py
diffusion_webui/utils/scheduler_list.py