Metadata-Version: 2.1
Name: diffusion-webui
Version: 2.5.0
Summary: PyTorch implementation of Diffusion Models
Home-page: https://github.com/kadirnar/diffusion-webui
Author: kadirnar
License: Open RAIL++-M
Keywords: diffusion,stable diffusion,controlnet,webui,image2image,text2image,inpaint,canny,depth,hed,mlsd,pose,seg,scribble
Classifier: Development Status :: 5 - Production/Stable
Classifier: Operating System :: OS Independent
Classifier: Intended Audience :: Developers
Classifier: Intended Audience :: Science/Research
Classifier: Programming Language :: Python :: 3
Classifier: Programming Language :: Python :: 3.7
Classifier: Programming Language :: Python :: 3.8
Classifier: Programming Language :: Python :: 3.9
Classifier: Topic :: Software Development :: Libraries
Classifier: Topic :: Software Development :: Libraries :: Python Modules
Classifier: Topic :: Education
Classifier: Topic :: Scientific/Engineering
Classifier: Topic :: Scientific/Engineering :: Artificial Intelligence
Requires-Python: >=3.6
License-File: LICENSE
